github_desktop_notifier/__init__.py
github_desktop_notifier/github.py
github_desktop_notifier/github_desktop_notifier.py
github_desktop_notifier-1.0.2.dist-info/LICENSE
github_desktop_notifier-1.0.2.dist-info/METADATA
github_desktop_notifier-1.0.2.dist-info/WHEEL
github_desktop_notifier-1.0.2.dist-info/entry_points.txt
github_desktop_notifier-1.0.2.dist-info/top_level.txt
github_desktop_notifier-1.0.2.dist-info/RECORD
