Metadata-Version: 2.1
Name: github-desktop-notifier
Version: 1.0.2
Summary: Receive instant GitHub notifications on your Linux desktop
Home-page: https://github.com/bytexenon/Github-Desktop-Notifier
Author: bytexenon
Author-email: ddavi142@asu.edu
License: MIT
Project-URL: Documentation, https://github.com/bytexenon/Github-Desktop-Notifier
Project-URL: Source, https://github.com/bytexenon/Github-Desktop-Notifier
Project-URL: Tracker, https://github.com/bytexenon/Github-Desktop-Notifier/issues
Project-URL: Changelog, https://github.com/bytexenon/Github-Desktop-Notifier/releases
Keywords: github desktop notifier linux notifications dunstify gh
Classifier: Development Status :: 4 - Beta
Classifier: Intended Audience :: Developers
Classifier: Topic :: Software Development :: Build Tools
Classifier: License :: OSI Approved :: MIT License
Classifier: Programming Language :: Python :: 3
Classifier: Programming Language :: Python :: 3.6
Classifier: Programming Language :: Python :: 3.7
Classifier: Programming Language :: Python :: 3.8
Classifier: Programming Language :: Python :: 3.9
Classifier: Programming Language :: Python :: 3.10
Classifier: Programming Language :: Python :: 3.11
Classifier: Programming Language :: Python :: 3.12
Requires-Python: >=3.6
License-File: LICENSE
Requires-Dist: requests
